package/__init__.py
package/subpckg1/EnergyRequirements.py
package/subpckg1/Goals.py
package/subpckg1/PersonalSummary.py
package/subpckg1/__init__.py
package/subpckg2/Macros.py
package/subpckg2/WorkoutSchedule.py
package/subpckg2/__init__.py
project_step_3-0.1.0.dist-info/LICENSE
project_step_3-0.1.0.dist-info/METADATA
project_step_3-0.1.0.dist-info/WHEEL
project_step_3-0.1.0.dist-info/top_level.txt
project_step_3-0.1.0.dist-info/RECORD
