Metadata-Version: 2.1
Name: project-step-3
Version: 0.1.0
Summary: A package for managing workouts, macros, and goals
Author-email: Suneet D'Silva <suneetdsilva@gmail.com>, Aamna Amer <aamna_a@live.com>
License: MIT
Project-URL: homepage, https://github.com/aamna-amer/project-step-3
Classifier: Programming Language :: Python :: 3
Classifier: License :: OSI Approved :: MIT License
Classifier: Operating System :: OS Independent
Requires-Python: >=3.6
License-File: LICENSE
Requires-Dist: tabulate>=0.9.0
